impc_api/__init__.py
impc_api/batch_solr_request.py
impc_api/solr_request.py
impc_api/utils/__init__.py
impc_api/utils/core_fields.json
impc_api/utils/validators.py
impc_api/utils/warnings.py
impc_api-1.0.7.dist-info/licenses/LICENSE
impc_api-1.0.7.dist-info/METADATA
impc_api-1.0.7.dist-info/WHEEL
impc_api-1.0.7.dist-info/top_level.txt
impc_api-1.0.7.dist-info/RECORD
