Metadata-Version: 2.4
Name: impc_api
Version: 1.0.7
Summary: A package to facilitate making API requests to the IMPC Solr API
Author: MPI2, Marina Kan, Diego Pava
Project-URL: Homepage, https://github.com/mpi2/impc-api
Requires-Python: >=3.10
License-File: LICENSE
Requires-Dist: ipykernel>=6.29.5
Requires-Dist: notebook>=7.2.2
Requires-Dist: pandas>=2.2.0
Requires-Dist: requests>=2.31.0
Requires-Dist: tqdm>=4.66.4
Requires-Dist: pydantic>=2.9
Provides-Extra: dev
Requires-Dist: pytest>=8.2.2; extra == "dev"
Dynamic: license-file
